kepler/__init__.py
kepler/reporting.py
kepler/timer.py
kepler_lib-0.1.dist-info/METADATA
kepler_lib-0.1.dist-info/WHEEL
kepler_lib-0.1.dist-info/RECORD
