Metadata-Version: 2.3
Name: kepler-lib
Version: 0.1
Summary: Fast, easy, pretty and readable program instrumentation.
Project-URL: Homepage, https://bethebunny.github.io/kepler
Project-URL: Documentation, https://bethebunny.github.io/kepler
Project-URL: Repository, https://github.com/bethebunny/kepler
Project-URL: Issues, https://github.com/bethebunny/kepler/issues
Project-URL: Changelog, https://github.com/bethebunny/kepler/releases
Author-email: Stef Lindall <bethebunny@gmail.com>
License: Copyright 2024 Stef Lindall, License BSD-3-Clause
Keywords: async,asyncio,instrument,instrumentation,profile,rich
Requires-Python: >=3.9
Requires-Dist: numpy
Requires-Dist: rich
